rest_framework_json_api/utils.py
rest_framework_json_api/__init__.py
rest_framework_json_api/parsers.py
rest_framework_json_api/renderers.py
rest_framework_json_api/encoders.py
drf_json_api-0.1.1.dist-info/WHEEL
drf_json_api-0.1.1.dist-info/metadata.json
drf_json_api-0.1.1.dist-info/RECORD
drf_json_api-0.1.1.dist-info/DESCRIPTION.rst
drf_json_api-0.1.1.dist-info/METADATA
drf_json_api-0.1.1.dist-info/top_level.txt
