Metadata-Version: 2.0
Name: drf-json-api
Version: 0.1.1
Summary: A parser and renderer for Django REST Framework that adds support for the JSON API specification.
Home-page: https://github.com/kevin-brown/drf-json-api
Author: Kevin Brown
Author-email: kevin@kevinbrown.in
License: MIT
Keywords: drf-json-api
Platform: UNKNOWN
Classifier: Development Status :: 2 - Pre-Alpha
Classifier: Intended Audience :: Developers
Classifier: License :: OSI Approved :: MIT License
Classifier: Natural Language :: English
Classifier: Programming Language :: Python :: 2
Classifier: Programming Language :: Python :: 2.7
Classifier: Programming Language :: Python :: 3
Classifier: Programming Language :: Python :: 3.2
Classifier: Programming Language :: Python :: 3.3
Classifier: Programming Language :: Python :: 3.4
Classifier: Programming Language :: Python :: Implementation :: PyPy
